spekk/__init__.py
spekk/spec.py
spekk/transformations/__init__.py
spekk/transformations/apply.py
spekk/transformations/axis.py
spekk/transformations/base.py
spekk/transformations/common.py
spekk/transformations/for_all.py
spekk/transformations/reduce.py
spekk/transformations/wrap.py
spekk/trees/__init__.py
spekk/trees/core.py
spekk/trees/registry.py
spekk/trees/treelens.py
spekk/util/__init__.py
spekk/util/flatten.py
spekk/util/shape.py
spekk/util/slicing.py
spekk/util/validation.py
spekk-1.0.9.dist-info/METADATA
spekk-1.0.9.dist-info/WHEEL
spekk-1.0.9.dist-info/licenses/LICENSE
spekk-1.0.9.dist-info/RECORD
