Metadata-Version: 2.3
Name: spekk
Version: 1.0.9
Summary: Named dimensions of nested arrays, independent of array implementation (Numpy, JAX, etc)
Project-URL: Homepage, https://github.com/magnusdk/spekk/
Project-URL: Documentation, https://spekk.readthedocs.io/en/latest/
Project-URL: Bug Tracker, https://github.com/magnusdk/spekk/issues
Author-email: Magnus Dalen Kvalevåg <magnus.kvalevag@ntnu.no>
Classifier: License :: OSI Approved :: Apache Software License
Classifier: Operating System :: OS Independent
Classifier: Programming Language :: Python :: 3
Requires-Python: >=3.9
Requires-Dist: numpy
